docs/conf.py
qtypy/__init__.py
qtypy/cli.py
qtypy/column.py
qtypy/dataflow.py
qtypy/dataset.py
qtypy/query.py
qtypy/selection.py
qtypy/cpp/__init__.py
qtypy/cpp/binding.py
qtypy/cpp/utils.py
queryosity_py-0.2.0.dist-info/licenses/LICENSE
queryosity_py-0.2.0.dist-info/METADATA
queryosity_py-0.2.0.dist-info/WHEEL
queryosity_py-0.2.0.dist-info/entry_points.txt
queryosity_py-0.2.0.dist-info/top_level.txt
queryosity_py-0.2.0.dist-info/RECORD
